{
  "$ref": "#/definitions/health",
  "definitions": {
    "health": {
      "type": "object",
      "properties": {
        "title": {
          "type": "string"
        },
        "description": {
          "type": "string"
        },
        "content": {
          "type": "string"
        },
        "countryId": {
          "type": "string"
        },
        "verifiedAt": {
          "type": "string",
          "format": "date-time"
        },
        "sourceAttribution": {
          "type": "string",
          "format": "uri"
        },
        "$schema": {
          "type": "string"
        }
      },
      "required": [
        "title",
        "description",
        "content",
        "countryId",
        "verifiedAt"
      ],
      "additionalProperties": false
    }
  },
  "$schema": "http://json-schema.org/draft-07/schema#"
}